LICENSE.txt
MANIFEST.in
README.srt
setup.py
febraban/__init__.py
febraban/cnab240/__init__.py
febraban/cnab240/characterType.py
febraban/cnab240/row.py
febraban/cnab240/user.py
febraban/cnab240/itau/__init__.py
febraban/cnab240/itau/charge/__init__.py
febraban/cnab240/itau/charge/file/__init__.py
febraban/cnab240/itau/charge/file/file.py
febraban/cnab240/itau/charge/file/header.py
febraban/cnab240/itau/charge/file/headerLot.py
febraban/cnab240/itau/charge/file/trailer.py
febraban/cnab240/itau/charge/file/trailerLot.py
febraban/cnab240/itau/charge/result/__init__.py
febraban/cnab240/itau/charge/result/errors.py
febraban/cnab240/itau/charge/result/occurrences.py
febraban/cnab240/itau/charge/result/parser.py
febraban/cnab240/itau/charge/slip/__init__.py
febraban/cnab240/itau/charge/slip/segmentP.py
febraban/cnab240/itau/charge/slip/segmentQ.py
febraban/cnab240/itau/charge/slip/segmentR.py
febraban/cnab240/itau/charge/slip/slip.py
febraban/cnab240/itau/sispag/__init__.py
febraban/cnab240/itau/sispag/file/__init__.py
febraban/cnab240/itau/sispag/file/file.py
febraban/cnab240/itau/sispag/file/header.py
febraban/cnab240/itau/sispag/file/trailer.py
febraban/cnab240/itau/sispag/payment/__init__.py
febraban/cnab240/itau/sispag/payment/chargePayment.py
febraban/cnab240/itau/sispag/payment/header.py
febraban/cnab240/itau/sispag/payment/segmentA.py
febraban/cnab240/itau/sispag/payment/segmentJ.py
febraban/cnab240/itau/sispag/payment/segmentJ52.py
febraban/cnab240/itau/sispag/payment/trailer.py
febraban/cnab240/itau/sispag/payment/transfer.py
febraban/cnab240/itau/sispag/result/__init__.py
febraban/cnab240/itau/sispag/result/occurrences.py
febraban/cnab240/itau/sispag/result/parser.py
febraban/cnab240/libs/__init__.py
febraban/cnab240/libs/barCode.py
febraban/cnab240/libs/dac.py
febraban/cnab240/libs/fileUtils.py
febraban/cnab240/libs/middlewares/__init__.py
febraban/cnab240/libs/middlewares/row.py
febraban_cnab.egg-info/PKG-INFO
febraban_cnab.egg-info/SOURCES.txt
febraban_cnab.egg-info/dependency_links.txt
febraban_cnab.egg-info/top_level.txt