Metadata-Version: 1.0
Name: febraban-cnab
Version: 0.0.1
Summary: A library to generate files in FEBRABAN CNAB formats
Home-page: https://github.com/starkbank/febraban.git
Author: danygregory
Author-email: dany.gregory@btgpactual.com
License: MIT License
Keywords: febraban,cnab,cnab 240,cnab240,febraban240,transfer,billing,bank
Platform: UNKNOWN
